solara_enterprise/__init__.py
solara_enterprise/license.py
solara_enterprise/ssg.py
solara_enterprise/auth/__init__.py
solara_enterprise/auth/components.py
solara_enterprise/auth/flask.py
solara_enterprise/auth/middleware.py
solara_enterprise/auth/starlette.py
solara_enterprise/auth/utils.py
solara_enterprise/cache/__init__.py
solara_enterprise/cache/base.py
solara_enterprise/cache/disk.py
solara_enterprise/cache/memory_size.py
solara_enterprise/cache/multi_level.py
solara_enterprise/cache/redis.py
solara_enterprise/search/__init__.py
solara_enterprise/search/index.py
solara_enterprise/search/search.py
solara_enterprise/search/search.vue
solara_enterprise-1.57.1.dist-info/METADATA
solara_enterprise-1.57.1.dist-info/WHEEL
solara_enterprise-1.57.1.dist-info/licenses/LICENSE
solara_enterprise-1.57.1.dist-info/RECORD
