Metadata-Version: 2.3
Name: solara-enterprise
Version: 1.57.1
Dynamic: Summary
Project-URL: Home, https://www.github.com/widgetti/solara
Author-email: "Maarten A. Breddels" <maartenbreddels@gmail.com>, Mario Buikhuizen <mariobuikhuizen@gmail.com>
License: Not open source, contact contact@solara.dev for licencing.
Classifier: License :: Free for non-commercial use
Requires-Python: >=3.8
Requires-Dist: solara-server==1.57.1
Requires-Dist: solara-ui==1.57.1
Provides-Extra: all
Requires-Dist: authlib; extra == 'all'
Requires-Dist: beautifulsoup4; extra == 'all'
Requires-Dist: diskcache; extra == 'all'
Requires-Dist: httpx; extra == 'all'
Requires-Dist: itsdangerous; extra == 'all'
Requires-Dist: playwright; extra == 'all'
Provides-Extra: auth
Requires-Dist: authlib; extra == 'auth'
Requires-Dist: httpx; extra == 'auth'
Requires-Dist: itsdangerous; extra == 'auth'
Provides-Extra: cache
Requires-Dist: diskcache; extra == 'cache'
Provides-Extra: ssg
Requires-Dist: beautifulsoup4; extra == 'ssg'
Requires-Dist: playwright; extra == 'ssg'
